emapi/__init__.py
emapi/base.py
emapi/constants.py
emapi/endpoints.py
emapi/events.py
emapi/filesystem.py
emapi/models.py
emapi/openapi.py
emapi/responses.py
emapi/server.py
emapi/templates.py
emapi/tools.py
emapi/exceptions/__init__.py
emapi/exceptions/auth.py
emapi/exceptions/base.py
emapi/exceptions/models.py
emapi/tortoise/__init__.py
emapi/tortoise/base.py
emapi/tortoise/utility.py
emapi-0.0.9.dist-info/LICENSE
emapi-0.0.9.dist-info/METADATA
emapi-0.0.9.dist-info/WHEEL
emapi-0.0.9.dist-info/top_level.txt
emapi-0.0.9.dist-info/RECORD
